odoo/addons/auth_oauth_multi_token/README.rst
odoo/addons/auth_oauth_multi_token/__init__.py
odoo/addons/auth_oauth_multi_token/__manifest__.py
odoo/addons/auth_oauth_multi_token/i18n/auth_oauth_multi_token.pot
odoo/addons/auth_oauth_multi_token/i18n/it.po
odoo/addons/auth_oauth_multi_token/models/__init__.py
odoo/addons/auth_oauth_multi_token/models/auth_oauth_multi_token.py
odoo/addons/auth_oauth_multi_token/models/res_users.py
odoo/addons/auth_oauth_multi_token/readme/CONFIGURATION.md
odoo/addons/auth_oauth_multi_token/readme/CONTRIBUTORS.md
odoo/addons/auth_oauth_multi_token/readme/DESCRIPTION.md
odoo/addons/auth_oauth_multi_token/readme/USAGE.md
odoo/addons/auth_oauth_multi_token/security/ir.model.access.csv
odoo/addons/auth_oauth_multi_token/static/description/icon.png
odoo/addons/auth_oauth_multi_token/static/description/index.html
odoo/addons/auth_oauth_multi_token/tests/__init__.py
odoo/addons/auth_oauth_multi_token/tests/test_multi_token.py
odoo/addons/auth_oauth_multi_token/views/auth_oauth_multi_token.xml
odoo/addons/auth_oauth_multi_token/views/res_users.xml
odoo_addon_auth_oauth_multi_token-18.0.2.0.0.1.dist-info/METADATA
odoo_addon_auth_oauth_multi_token-18.0.2.0.0.1.dist-info/WHEEL
odoo_addon_auth_oauth_multi_token-18.0.2.0.0.1.dist-info/top_level.txt
odoo_addon_auth_oauth_multi_token-18.0.2.0.0.1.dist-info/RECORD
