Metadata-Version: 2.1
Name: odoo-addon-auth_oauth_multi_token
Version: 18.0.2.0.0.1
Requires-Python: >=3.10
Requires-Dist: odoo==18.0.*
Summary: Allow multiple connection with the same OAuth account
Home-page: https://github.com/OCA/server-auth
License: AGPL-3
Author: Florent de Labarre, Camptocamp, Odoo Community Association (OCA)
Author-email: support@odoo-community.org
Classifier: Programming Language :: Python
Classifier: Framework :: Odoo
Classifier: Framework :: Odoo :: 18.0
Classifier: License :: OSI Approved :: GNU Affero General Public License v3
